[
  {
    "title": "Berserk",
    "author": "Miura  Kentarou",
    "chaptersInCart": 0,
    "image": "https://cdn.myanimelist.net/images/manga/1/157897l.jpg",
    "price": "12.32"
  },
  {
    "title": "Hajime no Ippo",
    "author": "Morikawa  George",
    "chaptersInCart": 0,
    "image": "https://cdn.myanimelist.net/images/manga/2/250313l.jpg",
    "price": "9.7"
  },
  {
    "title": "Naruto",
    "author": "Kishimoto  Masashi",
    "chaptersInCart": 0,
    "image": "https://cdn.myanimelist.net/images/manga/3/249658l.jpg",
    "price": "8.16"
  },
  {
    "title": "One Piece",
    "author": "Oda  Eiichiro",
    "chaptersInCart": 0,
    "image": "https://cdn.myanimelist.net/images/manga/2/253146l.jpg",
    "price": "13.27"
  },
  {
    "title": "Bleach",
    "author": "Kubo  Tite",
    "chaptersInCart": 0,
    "image": "https://cdn.myanimelist.net/images/manga/3/180031l.jpg",
    "price": "9.5"
  },
  {
    "title": "Hikaru no Go",
    "author": "Obata  Takeshi",
    "chaptersInCart": 0,
    "image": "https://cdn.myanimelist.net/images/manga/2/170574l.jpg",
    "price": "11.37"
  },
  {
    "title": "Death Note",
    "author": "Obata  Takeshi",
    "chaptersInCart": 0,
    "image": "https://cdn.myanimelist.net/images/manga/1/258245l.jpg",
    "price": "6.25"
  },
  {
    "title": "D.Gray-man",
    "author": "Hoshino  Katsura",
    "chaptersInCart": 0,
    "image": "https://cdn.myanimelist.net/images/manga/3/240470l.jpg",
    "price": "10.30"
  },
  {
    "title": "Fullmetal Alchemist",
    "author": "Arakawa  Hiromu",
    "chaptersInCart": 0,
    "image": "https://cdn.myanimelist.net/images/manga/3/243675l.jpg",
    "price": "14.22"
  }
]
